certbot_dns_local/__init__.py
certbot_dns_local/auth.py
certbot_dns_local/dns.py
certbot_dns_local/dnsutils.py
certbot_dns_local-0.1.1.dist-info/LICENSE.txt
certbot_dns_local-0.1.1.dist-info/METADATA
certbot_dns_local-0.1.1.dist-info/WHEEL
certbot_dns_local-0.1.1.dist-info/entry_points.txt
certbot_dns_local-0.1.1.dist-info/top_level.txt
certbot_dns_local-0.1.1.dist-info/RECORD
