Metadata-Version: 2.1
Name: certbot-dns-local
Version: 0.1.1
Summary: Domain registrar agnostic authenticator plugin for certbot
Home-page: https://github.com/blechschmidt/certbot-dns-local
Author: B. Blechschmidt
Author-email: github@blechschmidt.pw
License: Apache License 2.0
Platform: UNKNOWN
Classifier: Programming Language :: Python :: 2.7
Classifier: Programming Language :: Python :: 3
Classifier: License :: OSI Approved :: Apache Software License
Classifier: Intended Audience :: System Administrators
Classifier: Topic :: Internet :: Name Service (DNS)
Classifier: Topic :: Security :: Cryptography
Classifier: Development Status :: 4 - Beta
Classifier: Environment :: Plugins
Classifier: Operating System :: POSIX :: Linux
Requires-Dist: dnspython
Requires-Dist: NetfilterQueue
Requires-Dist: python-iptables
Requires-Dist: scapy
